merkury/__init__.py
merkury/main.py
merkury/renderer.py
merkury/runner_py.py
merkury/utils.py
merkury/templates/template.html
merkury/templates/template.md
merkury/templates/assets/merkury-themes.js
merkury/templates/assets/merkury.css
merkury/templates/assets/pico.min.css
merkury/templates/assets/prism-default.css
merkury/templates/assets/prism-night.css
merkury/templates/assets/prism.js
merkury-0.11.dist-info/licenses/LICENSE
merkury-0.11.dist-info/METADATA
merkury-0.11.dist-info/WHEEL
merkury-0.11.dist-info/entry_points.txt
merkury-0.11.dist-info/top_level.txt
merkury-0.11.dist-info/RECORD
