Metadata-Version: 2.4
Name: merkury
Version: 0.11
Summary: Turn Python scripts into HTML reports
Author: Piotr Patrzyk
License: MIT
Project-URL: Source, https://github.com/ppatrzyk/merkury
Keywords: analytics,reporting,data,data science
Classifier: Development Status :: 4 - Beta
Classifier: License :: OSI Approved :: MIT License
Classifier: Operating System :: OS Independent
Classifier: Programming Language :: Python :: 3
Classifier: Topic :: Database
Requires-Python: >=3.10
License-File: LICENSE
Requires-Dist: docopt==0.6.2
Requires-Dist: Jinja2==3.1.6
Requires-Dist: Markdown==3.10
Requires-Dist: MarkupSafe==3.0.3
Provides-Extra: test
Requires-Dist: pytest; extra == "test"
Dynamic: license-file
